CHANGES.txt
LICENSE.txt
MANIFEST.in
README.rst
coursera_offline.py
setup.py
coursera_offline.egg-info/PKG-INFO
coursera_offline.egg-info/SOURCES.txt
coursera_offline.egg-info/dependency_links.txt
coursera_offline.egg-info/requires.txt
coursera_offline.egg-info/top_level.txt