Metadata-Version: 1.0
Name: coursera-offline
Version: 1.0.2
Summary: Download Coursera videos for offline viewing
Home-page: https://github.com/sanketh95/coursera-offline
Author: Sanketh Mopuru
Author-email: sanketh.mopuru@gmail.com
License: GPLv3
Keywords: coursera offline download lecture lectures video videos
Platform: UNKNOWN
